{
  "baseline": {
    "n_households_m": 31.9,
    "current_cap": 1641,
    "mean_energy_spend": 2244,
    "total_energy_spend_bn": 71.5,
    "mean_net_income": 53895,
    "deciles": [
      {
        "decile": 1,
        "energy_spend": 2079,
        "net_income": 20096,
        "energy_share_pct": 10.3
      },
      {
        "decile": 2,
        "energy_spend": 1972,
        "net_income": 30739,
        "energy_share_pct": 6.4
      },
      {
        "decile": 3,
        "energy_spend": 1848,
        "net_income": 37045,
        "energy_share_pct": 5.0
      },
      {
        "decile": 4,
        "energy_spend": 2004,
        "net_income": 42406,
        "energy_share_pct": 4.7
      },
      {
        "decile": 5,
        "energy_spend": 2171,
        "net_income": 45823,
        "energy_share_pct": 4.7
      },
      {
        "decile": 6,
        "energy_spend": 2134,
        "net_income": 52290,
        "energy_share_pct": 4.1
      },
      {
        "decile": 7,
        "energy_spend": 2338,
        "net_income": 55377,
        "energy_share_pct": 4.2
      },
      {
        "decile": 8,
        "energy_spend": 2653,
        "net_income": 65925,
        "energy_share_pct": 4.0
      },
      {
        "decile": 9,
        "energy_spend": 2589,
        "net_income": 72922,
        "energy_share_pct": 3.6
      },
      {
        "decile": 10,
        "energy_spend": 2703,
        "net_income": 125456,
        "energy_share_pct": 2.2
      }
    ]
  },
  "shock_scenarios": [
    {
      "name": "+10%",
      "new_cap": 1805,
      "price_increase_pct": 10,
      "avg_hh_hit_yr": 224,
      "avg_hh_hit_mo": 19,
      "total_cost_bn": 7.1,
      "deciles": [
        {
          "decile": 1,
          "extra_cost": 208,
          "pct_of_income": 1.0
        },
        {
          "decile": 2,
          "extra_cost": 197,
          "pct_of_income": 0.6
        },
        {
          "decile": 3,
          "extra_cost": 185,
          "pct_of_income": 0.5
        },
        {
          "decile": 4,
          "extra_cost": 200,
          "pct_of_income": 0.5
        },
        {
          "decile": 5,
          "extra_cost": 217,
          "pct_of_income": 0.5
        },
        {
          "decile": 6,
          "extra_cost": 213,
          "pct_of_income": 0.4
        },
        {
          "decile": 7,
          "extra_cost": 234,
          "pct_of_income": 0.4
        },
        {
          "decile": 8,
          "extra_cost": 265,
          "pct_of_income": 0.4
        },
        {
          "decile": 9,
          "extra_cost": 259,
          "pct_of_income": 0.4
        },
        {
          "decile": 10,
          "extra_cost": 270,
          "pct_of_income": 0.2
        }
      ]
    },
    {
      "name": "+20%",
      "new_cap": 1969,
      "price_increase_pct": 20,
      "avg_hh_hit_yr": 448,
      "avg_hh_hit_mo": 37,
      "total_cost_bn": 14.3,
      "deciles": [
        {
          "decile": 1,
          "extra_cost": 416,
          "pct_of_income": 2.1
        },
        {
          "decile": 2,
          "extra_cost": 394,
          "pct_of_income": 1.3
        },
        {
          "decile": 3,
          "extra_cost": 369,
          "pct_of_income": 1.0
        },
        {
          "decile": 4,
          "extra_cost": 401,
          "pct_of_income": 0.9
        },
        {
          "decile": 5,
          "extra_cost": 434,
          "pct_of_income": 0.9
        },
        {
          "decile": 6,
          "extra_cost": 427,
          "pct_of_income": 0.8
        },
        {
          "decile": 7,
          "extra_cost": 467,
          "pct_of_income": 0.8
        },
        {
          "decile": 8,
          "extra_cost": 530,
          "pct_of_income": 0.8
        },
        {
          "decile": 9,
          "extra_cost": 518,
          "pct_of_income": 0.7
        },
        {
          "decile": 10,
          "extra_cost": 540,
          "pct_of_income": 0.4
        }
      ]
    },
    {
      "name": "+30%",
      "new_cap": 2133,
      "price_increase_pct": 30,
      "avg_hh_hit_yr": 673,
      "avg_hh_hit_mo": 56,
      "total_cost_bn": 21.4,
      "deciles": [
        {
          "decile": 1,
          "extra_cost": 623,
          "pct_of_income": 3.1
        },
        {
          "decile": 2,
          "extra_cost": 591,
          "pct_of_income": 1.9
        },
        {
          "decile": 3,
          "extra_cost": 554,
          "pct_of_income": 1.5
        },
        {
          "decile": 4,
          "extra_cost": 601,
          "pct_of_income": 1.4
        },
        {
          "decile": 5,
          "extra_cost": 651,
          "pct_of_income": 1.4
        },
        {
          "decile": 6,
          "extra_cost": 640,
          "pct_of_income": 1.2
        },
        {
          "decile": 7,
          "extra_cost": 701,
          "pct_of_income": 1.3
        },
        {
          "decile": 8,
          "extra_cost": 795,
          "pct_of_income": 1.2
        },
        {
          "decile": 9,
          "extra_cost": 776,
          "pct_of_income": 1.1
        },
        {
          "decile": 10,
          "extra_cost": 811,
          "pct_of_income": 0.6
        }
      ]
    },
    {
      "name": "+60%",
      "new_cap": 2625,
      "price_increase_pct": 60,
      "avg_hh_hit_yr": 1345,
      "avg_hh_hit_mo": 112,
      "total_cost_bn": 42.9,
      "deciles": [
        {
          "decile": 1,
          "extra_cost": 1247,
          "pct_of_income": 6.2
        },
        {
          "decile": 2,
          "extra_cost": 1183,
          "pct_of_income": 3.8
        },
        {
          "decile": 3,
          "extra_cost": 1108,
          "pct_of_income": 3.0
        },
        {
          "decile": 4,
          "extra_cost": 1202,
          "pct_of_income": 2.8
        },
        {
          "decile": 5,
          "extra_cost": 1302,
          "pct_of_income": 2.8
        },
        {
          "decile": 6,
          "extra_cost": 1280,
          "pct_of_income": 2.4
        },
        {
          "decile": 7,
          "extra_cost": 1402,
          "pct_of_income": 2.5
        },
        {
          "decile": 8,
          "extra_cost": 1591,
          "pct_of_income": 2.4
        },
        {
          "decile": 9,
          "extra_cost": 1553,
          "pct_of_income": 2.1
        },
        {
          "decile": 10,
          "extra_cost": 1621,
          "pct_of_income": 1.3
        }
      ]
    },
    {
      "name": "2022-level",
      "new_cap": 3764,
      "price_increase_pct": 129,
      "avg_hh_hit_yr": 2903,
      "avg_hh_hit_mo": 242,
      "total_cost_bn": 92.6,
      "deciles": [
        {
          "decile": 1,
          "extra_cost": 2690,
          "pct_of_income": 13.4
        },
        {
          "decile": 2,
          "extra_cost": 2552,
          "pct_of_income": 8.3
        },
        {
          "decile": 3,
          "extra_cost": 2390,
          "pct_of_income": 6.5
        },
        {
          "decile": 4,
          "extra_cost": 2592,
          "pct_of_income": 6.1
        },
        {
          "decile": 5,
          "extra_cost": 2809,
          "pct_of_income": 6.1
        },
        {
          "decile": 6,
          "extra_cost": 2761,
          "pct_of_income": 5.3
        },
        {
          "decile": 7,
          "extra_cost": 3025,
          "pct_of_income": 5.5
        },
        {
          "decile": 8,
          "extra_cost": 3432,
          "pct_of_income": 5.2
        },
        {
          "decile": 9,
          "extra_cost": 3350,
          "pct_of_income": 4.6
        },
        {
          "decile": 10,
          "extra_cost": 3498,
          "pct_of_income": 2.8
        }
      ]
    }
  ],
  "fuel_poverty": [
    {
      "scenario": "Baseline (current prices)",
      "fuel_poverty_rate_pct": 14.4,
      "households_m": 4.6,
      "extra_households_m": 0
    },
    {
      "scenario": "+10% (cap -> 1805)",
      "fuel_poverty_rate_pct": 16.3,
      "households_m": 5.2,
      "extra_households_m": 0.6
    },
    {
      "scenario": "+20% (cap -> 1969)",
      "fuel_poverty_rate_pct": 19.2,
      "households_m": 6.1,
      "extra_households_m": 1.5
    },
    {
      "scenario": "+30% (cap -> 2133)",
      "fuel_poverty_rate_pct": 21.3,
      "households_m": 6.8,
      "extra_households_m": 2.2
    },
    {
      "scenario": "+60% (cap -> 2625)",
      "fuel_poverty_rate_pct": 29.9,
      "households_m": 9.5,
      "extra_households_m": 5.0
    },
    {
      "scenario": "2022-level (cap -> 3764)",
      "fuel_poverty_rate_pct": 46.5,
      "households_m": 14.8,
      "extra_households_m": 10.2
    }
  ],
  "policies": {
    "epg": {
      "name": "EPG subsidy",
      "description": "Energy Price Guarantee at 2500",
      "exchequer_cost_bn": 0.4,
      "avg_hh_benefit": 12,
      "deciles": [
        {
          "decile": 1,
          "payment": 11,
          "shock_offset_pct": 1
        },
        {
          "decile": 2,
          "payment": 11,
          "shock_offset_pct": 1
        },
        {
          "decile": 3,
          "payment": 10,
          "shock_offset_pct": 1
        },
        {
          "decile": 4,
          "payment": 11,
          "shock_offset_pct": 1
        },
        {
          "decile": 5,
          "payment": 12,
          "shock_offset_pct": 1
        },
        {
          "decile": 6,
          "payment": 12,
          "shock_offset_pct": 1
        },
        {
          "decile": 7,
          "payment": 13,
          "shock_offset_pct": 1
        },
        {
          "decile": 8,
          "payment": 15,
          "shock_offset_pct": 1
        },
        {
          "decile": 9,
          "payment": 14,
          "shock_offset_pct": 1
        },
        {
          "decile": 10,
          "payment": 15,
          "shock_offset_pct": 1
        }
      ]
    },
    "flat_transfer": {
      "name": "Flat transfer",
      "description": "400 per household",
      "exchequer_cost_bn": 12.8,
      "avg_hh_benefit": 400,
      "deciles": [
        {
          "decile": 1,
          "payment": 400,
          "shock_offset_pct": 32
        },
        {
          "decile": 2,
          "payment": 400,
          "shock_offset_pct": 34
        },
        {
          "decile": 3,
          "payment": 400,
          "shock_offset_pct": 36
        },
        {
          "decile": 4,
          "payment": 400,
          "shock_offset_pct": 33
        },
        {
          "decile": 5,
          "payment": 400,
          "shock_offset_pct": 31
        },
        {
          "decile": 6,
          "payment": 400,
          "shock_offset_pct": 31
        },
        {
          "decile": 7,
          "payment": 400,
          "shock_offset_pct": 29
        },
        {
          "decile": 8,
          "payment": 400,
          "shock_offset_pct": 25
        },
        {
          "decile": 9,
          "payment": 400,
          "shock_offset_pct": 26
        },
        {
          "decile": 10,
          "payment": 400,
          "shock_offset_pct": 25
        }
      ]
    },
    "ct_rebate": {
      "name": "CT band rebate",
      "description": "300 for bands A-D",
      "exchequer_cost_bn": 7.7,
      "avg_hh_benefit": 240,
      "deciles": [
        {
          "decile": 1,
          "payment": 246,
          "shock_offset_pct": 20
        },
        {
          "decile": 2,
          "payment": 261,
          "shock_offset_pct": 22
        },
        {
          "decile": 3,
          "payment": 283,
          "shock_offset_pct": 26
        },
        {
          "decile": 4,
          "payment": 243,
          "shock_offset_pct": 20
        },
        {
          "decile": 5,
          "payment": 251,
          "shock_offset_pct": 19
        },
        {
          "decile": 6,
          "payment": 247,
          "shock_offset_pct": 19
        },
        {
          "decile": 7,
          "payment": 241,
          "shock_offset_pct": 17
        },
        {
          "decile": 8,
          "payment": 221,
          "shock_offset_pct": 14
        },
        {
          "decile": 9,
          "payment": 225,
          "shock_offset_pct": 14
        },
        {
          "decile": 10,
          "payment": 185,
          "shock_offset_pct": 11
        }
      ]
    },
    "winter_fuel": {
      "name": "Expanded winter fuel",
      "description": "Universal for pensioners, 350/500",
      "exchequer_cost_bn": 1.5,
      "total_spending_bn": 3.3,
      "avg_hh_benefit": 104,
      "deciles": [
        {
          "decile": 1,
          "payment": 143,
          "extra_vs_baseline": 59
        },
        {
          "decile": 2,
          "payment": 191,
          "extra_vs_baseline": 78
        },
        {
          "decile": 3,
          "payment": 108,
          "extra_vs_baseline": 43
        },
        {
          "decile": 4,
          "payment": 120,
          "extra_vs_baseline": 55
        },
        {
          "decile": 5,
          "payment": 109,
          "extra_vs_baseline": 47
        },
        {
          "decile": 6,
          "payment": 101,
          "extra_vs_baseline": 52
        },
        {
          "decile": 7,
          "payment": 80,
          "extra_vs_baseline": 45
        },
        {
          "decile": 8,
          "payment": 57,
          "extra_vs_baseline": 31
        },
        {
          "decile": 9,
          "payment": 51,
          "extra_vs_baseline": 30
        },
        {
          "decile": 10,
          "payment": 62,
          "extra_vs_baseline": 37
        }
      ]
    },
    "combined": {
      "name": "Combined package",
      "description": "EPG + flat transfer + CT rebate + expanded WFA",
      "exchequer_cost_bn": 22.3,
      "component_costs_bn": {
        "epg": 0.4,
        "flat_transfer": 12.8,
        "ct_rebate": 7.7,
        "extra_wfa": 1.5
      },
      "avg_net_income_change": 701,
      "deciles": [
        {
          "decile": 1,
          "net_income_change": 747,
          "pct_change": 3.7
        },
        {
          "decile": 2,
          "net_income_change": 746,
          "pct_change": 2.4
        },
        {
          "decile": 3,
          "net_income_change": 726,
          "pct_change": 2.0
        },
        {
          "decile": 4,
          "net_income_change": 614,
          "pct_change": 1.4
        },
        {
          "decile": 5,
          "net_income_change": 787,
          "pct_change": 1.7
        },
        {
          "decile": 6,
          "net_income_change": 664,
          "pct_change": 1.3
        },
        {
          "decile": 7,
          "net_income_change": 658,
          "pct_change": 1.2
        },
        {
          "decile": 8,
          "net_income_change": 675,
          "pct_change": 1.0
        },
        {
          "decile": 9,
          "net_income_change": 610,
          "pct_change": 0.8
        },
        {
          "decile": 10,
          "net_income_change": 622,
          "pct_change": 0.5
        }
      ]
    }
  },
  "config": {
    "year": 2026,
    "current_cap": 1641,
    "shock_cap": 2625,
    "epg_target": 2500,
    "flat_transfer": 400,
    "ct_rebate": 300
  }
}