{
  "energy_split": {
    "mean_electricity": 860,
    "mean_gas": 700,
    "mean_total": 1560,
    "elec_share_pct": 55.1,
    "deciles": [
      {
        "decile": 1,
        "electricity": 757,
        "gas": 631,
        "total_energy": 1388,
        "net_income": 20044,
        "elec_share_pct": 54.5,
        "elec_burden_pct": 3.8,
        "gas_burden_pct": 3.1
      },
      {
        "decile": 2,
        "electricity": 810,
        "gas": 649,
        "total_energy": 1460,
        "net_income": 30931,
        "elec_share_pct": 55.5,
        "elec_burden_pct": 2.6,
        "gas_burden_pct": 2.1
      },
      {
        "decile": 3,
        "electricity": 765,
        "gas": 604,
        "total_energy": 1370,
        "net_income": 37529,
        "elec_share_pct": 55.9,
        "elec_burden_pct": 2.0,
        "gas_burden_pct": 1.6
      },
      {
        "decile": 4,
        "electricity": 833,
        "gas": 681,
        "total_energy": 1513,
        "net_income": 42174,
        "elec_share_pct": 55.0,
        "elec_burden_pct": 2.0,
        "gas_burden_pct": 1.6
      },
      {
        "decile": 5,
        "electricity": 814,
        "gas": 701,
        "total_energy": 1515,
        "net_income": 44158,
        "elec_share_pct": 53.7,
        "elec_burden_pct": 1.8,
        "gas_burden_pct": 1.6
      },
      {
        "decile": 6,
        "electricity": 882,
        "gas": 731,
        "total_energy": 1613,
        "net_income": 51600,
        "elec_share_pct": 54.7,
        "elec_burden_pct": 1.7,
        "gas_burden_pct": 1.4
      },
      {
        "decile": 7,
        "electricity": 863,
        "gas": 654,
        "total_energy": 1518,
        "net_income": 56013,
        "elec_share_pct": 56.9,
        "elec_burden_pct": 1.5,
        "gas_burden_pct": 1.2
      },
      {
        "decile": 8,
        "electricity": 928,
        "gas": 742,
        "total_energy": 1670,
        "net_income": 67097,
        "elec_share_pct": 55.6,
        "elec_burden_pct": 1.4,
        "gas_burden_pct": 1.1
      },
      {
        "decile": 9,
        "electricity": 935,
        "gas": 809,
        "total_energy": 1744,
        "net_income": 73807,
        "elec_share_pct": 53.6,
        "elec_burden_pct": 1.3,
        "gas_burden_pct": 1.1
      },
      {
        "decile": 10,
        "electricity": 953,
        "gas": 749,
        "total_energy": 1702,
        "net_income": 125107,
        "elec_share_pct": 56.0,
        "elec_burden_pct": 0.8,
        "gas_burden_pct": 0.6
      }
    ]
  },
  "tenure": [
    {
      "tenure": "OWNED_OUTRIGHT",
      "electricity": 1015,
      "gas": 874,
      "total_energy": 1888,
      "net_income": 49732,
      "energy_burden_pct": 3.8,
      "fuel_poverty_pct": 15.3,
      "households_m": 10.8
    },
    {
      "tenure": "RENT_FROM_HA",
      "electricity": 697,
      "gas": 485,
      "total_energy": 1182,
      "net_income": 37000,
      "energy_burden_pct": 3.2,
      "fuel_poverty_pct": 6.0,
      "households_m": 3.4
    },
    {
      "tenure": "RENT_FROM_COUNCIL",
      "electricity": 672,
      "gas": 463,
      "total_energy": 1135,
      "net_income": 36894,
      "energy_burden_pct": 3.1,
      "fuel_poverty_pct": 6.5,
      "households_m": 2.4
    },
    {
      "tenure": "RENT_PRIVATELY",
      "electricity": 782,
      "gas": 591,
      "total_energy": 1373,
      "net_income": 53894,
      "energy_burden_pct": 2.5,
      "fuel_poverty_pct": 8.0,
      "households_m": 7.0
    },
    {
      "tenure": "OWNED_WITH_MORTGAGE",
      "electricity": 845,
      "gas": 721,
      "total_energy": 1567,
      "net_income": 71268,
      "energy_burden_pct": 2.2,
      "fuel_poverty_pct": 4.8,
      "households_m": 8.3
    }
  ],
  "household_type": [
    {
      "hh_type": "SINGLE_PENSIONER",
      "electricity": 858,
      "gas": 699,
      "total_energy": 1557,
      "net_income": 24294,
      "energy_burden_pct": 6.4,
      "fuel_poverty_pct": 20.4,
      "households_m": 3.9
    },
    {
      "hh_type": "SINGLE_WORKING_AGE",
      "electricity": 772,
      "gas": 604,
      "total_energy": 1376,
      "net_income": 31127,
      "energy_burden_pct": 4.4,
      "fuel_poverty_pct": 16.1,
      "households_m": 5.7
    },
    {
      "hh_type": "COUPLE_PENSIONER",
      "electricity": 963,
      "gas": 801,
      "total_energy": 1764,
      "net_income": 52279,
      "energy_burden_pct": 3.4,
      "fuel_poverty_pct": 7.8,
      "households_m": 4.5
    },
    {
      "hh_type": "LONE_PARENT",
      "electricity": 751,
      "gas": 598,
      "total_energy": 1350,
      "net_income": 39521,
      "energy_burden_pct": 3.4,
      "fuel_poverty_pct": 8.0,
      "households_m": 2.1
    },
    {
      "hh_type": "COUPLE_NO_CHILDREN",
      "electricity": 941,
      "gas": 764,
      "total_energy": 1705,
      "net_income": 65434,
      "energy_burden_pct": 2.6,
      "fuel_poverty_pct": 6.8,
      "households_m": 7.8
    },
    {
      "hh_type": "COUPLE_WITH_CHILDREN",
      "electricity": 804,
      "gas": 662,
      "total_energy": 1466,
      "net_income": 71894,
      "energy_burden_pct": 2.0,
      "fuel_poverty_pct": 2.8,
      "households_m": 5.7
    },
    {
      "hh_type": "OTHER",
      "electricity": 844,
      "gas": 710,
      "total_energy": 1554,
      "net_income": 94546,
      "energy_burden_pct": 1.6,
      "fuel_poverty_pct": 2.4,
      "households_m": 2.2
    }
  ],
  "country": [
    {
      "country": "NORTHERN_IRELAND",
      "electricity": 1049,
      "gas": 865,
      "total_energy": 1915,
      "net_income": 54871,
      "energy_burden_pct": 3.5,
      "fuel_poverty_pct": 11.8,
      "households_m": 0.8
    },
    {
      "country": "SCOTLAND",
      "electricity": 896,
      "gas": 673,
      "total_energy": 1569,
      "net_income": 50808,
      "energy_burden_pct": 3.1,
      "fuel_poverty_pct": 7.3,
      "households_m": 2.7
    },
    {
      "country": "ENGLAND",
      "electricity": 859,
      "gas": 705,
      "total_energy": 1564,
      "net_income": 54505,
      "energy_burden_pct": 2.9,
      "fuel_poverty_pct": 9.6,
      "households_m": 26.8
    },
    {
      "country": "WALES",
      "electricity": 735,
      "gas": 576,
      "total_energy": 1311,
      "net_income": 49379,
      "energy_burden_pct": 2.7,
      "fuel_poverty_pct": 6.3,
      "households_m": 1.5
    }
  ],
  "neg_policy": {
    "name": "NEF National Energy Guarantee",
    "description": "Subsidise first 2,900 kWh of electricity per household (\u00a3793 at current rates). Progressive because low users get most or all of their electricity covered.",
    "threshold_kwh": 2900,
    "threshold_spend": 793,
    "baseline_cost_bn": 17.9,
    "avg_benefit_baseline": 562,
    "deciles_baseline": [
      {
        "decile": 1,
        "benefit": 501,
        "elec_spend": 757,
        "coverage_pct": 66.1
      },
      {
        "decile": 2,
        "benefit": 547,
        "elec_spend": 810,
        "coverage_pct": 67.6
      },
      {
        "decile": 3,
        "benefit": 546,
        "elec_spend": 765,
        "coverage_pct": 71.3
      },
      {
        "decile": 4,
        "benefit": 539,
        "elec_spend": 833,
        "coverage_pct": 64.7
      },
      {
        "decile": 5,
        "benefit": 556,
        "elec_spend": 814,
        "coverage_pct": 68.3
      },
      {
        "decile": 6,
        "benefit": 580,
        "elec_spend": 882,
        "coverage_pct": 65.8
      },
      {
        "decile": 7,
        "benefit": 606,
        "elec_spend": 863,
        "coverage_pct": 70.2
      },
      {
        "decile": 8,
        "benefit": 611,
        "elec_spend": 928,
        "coverage_pct": 65.8
      },
      {
        "decile": 9,
        "benefit": 565,
        "elec_spend": 935,
        "coverage_pct": 60.4
      },
      {
        "decile": 10,
        "benefit": 581,
        "elec_spend": 953,
        "coverage_pct": 60.9
      }
    ],
    "scenarios": [
      {
        "name": "+10%",
        "new_cap": 1805,
        "exchequer_cost_bn": 19.7,
        "avg_benefit": 618,
        "avg_net_extra_cost": 100,
        "deciles": [
          {
            "decile": 1,
            "benefit": 551,
            "shock_extra": 139,
            "benefit_extra_vs_baseline": 50,
            "offset_pct": 36.1
          },
          {
            "decile": 2,
            "benefit": 602,
            "shock_extra": 146,
            "benefit_extra_vs_baseline": 55,
            "offset_pct": 37.5
          },
          {
            "decile": 3,
            "benefit": 600,
            "shock_extra": 137,
            "benefit_extra_vs_baseline": 55,
            "offset_pct": 39.9
          },
          {
            "decile": 4,
            "benefit": 593,
            "shock_extra": 151,
            "benefit_extra_vs_baseline": 54,
            "offset_pct": 35.6
          },
          {
            "decile": 5,
            "benefit": 612,
            "shock_extra": 151,
            "benefit_extra_vs_baseline": 56,
            "offset_pct": 36.7
          },
          {
            "decile": 6,
            "benefit": 638,
            "shock_extra": 161,
            "benefit_extra_vs_baseline": 58,
            "offset_pct": 36.0
          },
          {
            "decile": 7,
            "benefit": 667,
            "shock_extra": 152,
            "benefit_extra_vs_baseline": 61,
            "offset_pct": 40.0
          },
          {
            "decile": 8,
            "benefit": 672,
            "shock_extra": 167,
            "benefit_extra_vs_baseline": 61,
            "offset_pct": 36.6
          },
          {
            "decile": 9,
            "benefit": 621,
            "shock_extra": 174,
            "benefit_extra_vs_baseline": 56,
            "offset_pct": 32.4
          },
          {
            "decile": 10,
            "benefit": 639,
            "shock_extra": 170,
            "benefit_extra_vs_baseline": 58,
            "offset_pct": 34.1
          }
        ]
      },
      {
        "name": "+20%",
        "new_cap": 1969,
        "exchequer_cost_bn": 21.5,
        "avg_benefit": 674,
        "avg_net_extra_cost": 200,
        "deciles": [
          {
            "decile": 1,
            "benefit": 601,
            "shock_extra": 277,
            "benefit_extra_vs_baseline": 100,
            "offset_pct": 36.1
          },
          {
            "decile": 2,
            "benefit": 657,
            "shock_extra": 292,
            "benefit_extra_vs_baseline": 109,
            "offset_pct": 37.5
          },
          {
            "decile": 3,
            "benefit": 655,
            "shock_extra": 274,
            "benefit_extra_vs_baseline": 109,
            "offset_pct": 39.9
          },
          {
            "decile": 4,
            "benefit": 647,
            "shock_extra": 302,
            "benefit_extra_vs_baseline": 108,
            "offset_pct": 35.6
          },
          {
            "decile": 5,
            "benefit": 667,
            "shock_extra": 303,
            "benefit_extra_vs_baseline": 111,
            "offset_pct": 36.7
          },
          {
            "decile": 6,
            "benefit": 696,
            "shock_extra": 322,
            "benefit_extra_vs_baseline": 116,
            "offset_pct": 36.0
          },
          {
            "decile": 7,
            "benefit": 728,
            "shock_extra": 303,
            "benefit_extra_vs_baseline": 121,
            "offset_pct": 40.0
          },
          {
            "decile": 8,
            "benefit": 733,
            "shock_extra": 334,
            "benefit_extra_vs_baseline": 122,
            "offset_pct": 36.6
          },
          {
            "decile": 9,
            "benefit": 678,
            "shock_extra": 349,
            "benefit_extra_vs_baseline": 113,
            "offset_pct": 32.4
          },
          {
            "decile": 10,
            "benefit": 697,
            "shock_extra": 340,
            "benefit_extra_vs_baseline": 116,
            "offset_pct": 34.1
          }
        ]
      },
      {
        "name": "+30%",
        "new_cap": 2133,
        "exchequer_cost_bn": 23.3,
        "avg_benefit": 730,
        "avg_net_extra_cost": 299,
        "deciles": [
          {
            "decile": 1,
            "benefit": 651,
            "shock_extra": 416,
            "benefit_extra_vs_baseline": 150,
            "offset_pct": 36.1
          },
          {
            "decile": 2,
            "benefit": 712,
            "shock_extra": 438,
            "benefit_extra_vs_baseline": 164,
            "offset_pct": 37.5
          },
          {
            "decile": 3,
            "benefit": 710,
            "shock_extra": 411,
            "benefit_extra_vs_baseline": 164,
            "offset_pct": 39.9
          },
          {
            "decile": 4,
            "benefit": 701,
            "shock_extra": 454,
            "benefit_extra_vs_baseline": 162,
            "offset_pct": 35.6
          },
          {
            "decile": 5,
            "benefit": 723,
            "shock_extra": 454,
            "benefit_extra_vs_baseline": 167,
            "offset_pct": 36.7
          },
          {
            "decile": 6,
            "benefit": 754,
            "shock_extra": 484,
            "benefit_extra_vs_baseline": 174,
            "offset_pct": 36.0
          },
          {
            "decile": 7,
            "benefit": 788,
            "shock_extra": 455,
            "benefit_extra_vs_baseline": 182,
            "offset_pct": 40.0
          },
          {
            "decile": 8,
            "benefit": 794,
            "shock_extra": 501,
            "benefit_extra_vs_baseline": 183,
            "offset_pct": 36.6
          },
          {
            "decile": 9,
            "benefit": 734,
            "shock_extra": 523,
            "benefit_extra_vs_baseline": 169,
            "offset_pct": 32.4
          },
          {
            "decile": 10,
            "benefit": 755,
            "shock_extra": 510,
            "benefit_extra_vs_baseline": 174,
            "offset_pct": 34.1
          }
        ]
      },
      {
        "name": "+60%",
        "new_cap": 2625,
        "exchequer_cost_bn": 28.6,
        "avg_benefit": 899,
        "avg_net_extra_cost": 599,
        "deciles": [
          {
            "decile": 1,
            "benefit": 801,
            "shock_extra": 832,
            "benefit_extra_vs_baseline": 300,
            "offset_pct": 36.1
          },
          {
            "decile": 2,
            "benefit": 876,
            "shock_extra": 875,
            "benefit_extra_vs_baseline": 328,
            "offset_pct": 37.5
          },
          {
            "decile": 3,
            "benefit": 873,
            "shock_extra": 821,
            "benefit_extra_vs_baseline": 327,
            "offset_pct": 39.9
          },
          {
            "decile": 4,
            "benefit": 862,
            "shock_extra": 907,
            "benefit_extra_vs_baseline": 323,
            "offset_pct": 35.6
          },
          {
            "decile": 5,
            "benefit": 890,
            "shock_extra": 909,
            "benefit_extra_vs_baseline": 334,
            "offset_pct": 36.7
          },
          {
            "decile": 6,
            "benefit": 928,
            "shock_extra": 967,
            "benefit_extra_vs_baseline": 348,
            "offset_pct": 36.0
          },
          {
            "decile": 7,
            "benefit": 970,
            "shock_extra": 910,
            "benefit_extra_vs_baseline": 364,
            "offset_pct": 40.0
          },
          {
            "decile": 8,
            "benefit": 978,
            "shock_extra": 1001,
            "benefit_extra_vs_baseline": 366,
            "offset_pct": 36.6
          },
          {
            "decile": 9,
            "benefit": 903,
            "shock_extra": 1046,
            "benefit_extra_vs_baseline": 339,
            "offset_pct": 32.4
          },
          {
            "decile": 10,
            "benefit": 929,
            "shock_extra": 1021,
            "benefit_extra_vs_baseline": 348,
            "offset_pct": 34.1
          }
        ]
      },
      {
        "name": "2022-level",
        "new_cap": 3764,
        "exchequer_cost_bn": 41.1,
        "avg_benefit": 1289,
        "avg_net_extra_cost": 1292,
        "deciles": [
          {
            "decile": 1,
            "benefit": 1148,
            "shock_extra": 1795,
            "benefit_extra_vs_baseline": 648,
            "offset_pct": 36.1
          },
          {
            "decile": 2,
            "benefit": 1256,
            "shock_extra": 1888,
            "benefit_extra_vs_baseline": 708,
            "offset_pct": 37.5
          },
          {
            "decile": 3,
            "benefit": 1252,
            "shock_extra": 1772,
            "benefit_extra_vs_baseline": 706,
            "offset_pct": 39.9
          },
          {
            "decile": 4,
            "benefit": 1237,
            "shock_extra": 1958,
            "benefit_extra_vs_baseline": 698,
            "offset_pct": 35.6
          },
          {
            "decile": 5,
            "benefit": 1276,
            "shock_extra": 1960,
            "benefit_extra_vs_baseline": 720,
            "offset_pct": 36.7
          },
          {
            "decile": 6,
            "benefit": 1331,
            "shock_extra": 2086,
            "benefit_extra_vs_baseline": 751,
            "offset_pct": 36.0
          },
          {
            "decile": 7,
            "benefit": 1391,
            "shock_extra": 1964,
            "benefit_extra_vs_baseline": 784,
            "offset_pct": 40.0
          },
          {
            "decile": 8,
            "benefit": 1402,
            "shock_extra": 2160,
            "benefit_extra_vs_baseline": 791,
            "offset_pct": 36.6
          },
          {
            "decile": 9,
            "benefit": 1295,
            "shock_extra": 2257,
            "benefit_extra_vs_baseline": 730,
            "offset_pct": 32.4
          },
          {
            "decile": 10,
            "benefit": 1332,
            "shock_extra": 2202,
            "benefit_extra_vs_baseline": 751,
            "offset_pct": 34.1
          }
        ]
      }
    ]
  },
  "rising_block_tariff": {
    "name": "Rising block tariff (cost-neutral)",
    "description": "50% discount on first 2,900 kWh of electricity, funded by a 94.2% surcharge on consumption above that level. Zero exchequer cost \u2014 high users cross-subsidise low users.",
    "threshold_kwh": 2900,
    "threshold_spend": 793,
    "discount_rate_pct": 50,
    "surcharge_rate_pct": 94.2,
    "exchequer_cost_bn": 0,
    "total_subsidy_bn": 9.0,
    "deciles": [
      {
        "decile": 1,
        "elec_spend": 757,
        "block1_spend": 501,
        "block2_spend": 256,
        "block1_saving": 250,
        "block2_surcharge": 241,
        "net_effect": -9,
        "net_pct_income": -0.04
      },
      {
        "decile": 2,
        "elec_spend": 810,
        "block1_spend": 547,
        "block2_spend": 263,
        "block1_saving": 274,
        "block2_surcharge": 248,
        "net_effect": -26,
        "net_pct_income": -0.08
      },
      {
        "decile": 3,
        "elec_spend": 765,
        "block1_spend": 546,
        "block2_spend": 219,
        "block1_saving": 273,
        "block2_surcharge": 207,
        "net_effect": -66,
        "net_pct_income": -0.18
      },
      {
        "decile": 4,
        "elec_spend": 833,
        "block1_spend": 539,
        "block2_spend": 294,
        "block1_saving": 270,
        "block2_surcharge": 276,
        "net_effect": 7,
        "net_pct_income": 0.02
      },
      {
        "decile": 5,
        "elec_spend": 814,
        "block1_spend": 556,
        "block2_spend": 258,
        "block1_saving": 278,
        "block2_surcharge": 243,
        "net_effect": -35,
        "net_pct_income": -0.08
      },
      {
        "decile": 6,
        "elec_spend": 882,
        "block1_spend": 580,
        "block2_spend": 301,
        "block1_saving": 290,
        "block2_surcharge": 284,
        "net_effect": -6,
        "net_pct_income": -0.01
      },
      {
        "decile": 7,
        "elec_spend": 863,
        "block1_spend": 606,
        "block2_spend": 257,
        "block1_saving": 303,
        "block2_surcharge": 242,
        "net_effect": -61,
        "net_pct_income": -0.11
      },
      {
        "decile": 8,
        "elec_spend": 928,
        "block1_spend": 611,
        "block2_spend": 317,
        "block1_saving": 306,
        "block2_surcharge": 298,
        "net_effect": -7,
        "net_pct_income": -0.01
      },
      {
        "decile": 9,
        "elec_spend": 935,
        "block1_spend": 565,
        "block2_spend": 370,
        "block1_saving": 282,
        "block2_surcharge": 349,
        "net_effect": 67,
        "net_pct_income": 0.09
      },
      {
        "decile": 10,
        "elec_spend": 953,
        "block1_spend": 581,
        "block2_spend": 373,
        "block1_saving": 290,
        "block2_surcharge": 351,
        "net_effect": 60,
        "net_pct_income": 0.05
      }
    ]
  }
}